Stilix.py
Stilix_data_change.py
__init__.py
d_tool.py
extra_layer.py
ladder_hewn.py
Stilix-1.0.dist-info/METADATA
Stilix-1.0.dist-info/WHEEL
Stilix-1.0.dist-info/top_level.txt
Stilix-1.0.dist-info/RECORD
